Metadata-Version: 2.1
Name: proofproposition
Version: 0.0.1
Summary: Proposition Logic
Home-page: https://github.com/HappyMayzhang/proofproposition
Author: may.xiaoya.zhang
Author-email: may.xiaoya.zhang@gmail.com
Classifier: Programming Language :: Python :: 3
Classifier: License :: OSI Approved :: MIT License
Classifier: Operating System :: OS Independent
Requires-Python: >=3.11.3
Requires-Dist: TatSu>=5.12.0
